<?xml version='1.0' encoding='utf-8'?>
<!DOCTYPE hibernate-configuration PUBLIC
        "-//Hibernate/Hibernate Configuration DTD 3.0//EN"
        "http://www.hibernate.org/dtd/hibernate-configuration-3.0.dtd">
<hibernate-configuration>
    <session-factory>
        <!--<mapping class="by.bsuir.lingvicic.bean.ContactPerson"/>
        <mapping class="by.bsuir.lingvicic.bean.Menu"/>
        <mapping class="by.bsuir.lingvicic.bean.User"/>
        <mapping class="by.bsuir.lingvicic.bean.Student"/>
        <mapping class="by.bsuir.lingvicic.bean.Participant"/>
        <mapping class="by.bsuir.lingvicic.bean.education.Faculty"/>
        <mapping class="by.bsuir.lingvicic.bean.education.University"/>
        <mapping class="by.bsuir.lingvicic.bean.education.Speciality"/>
        <mapping class="by.bsuir.lingvicic.bean.Role"/>
        <mapping class="by.bsuir.lingvicic.bean.CourseWork"/>-->
    </session-factory>
</hibernate-configuration>